LICENSE
README.md
setup.py
pypi_scraper/__init__.py
telegram_scraper.egg-info/PKG-INFO
telegram_scraper.egg-info/SOURCES.txt
telegram_scraper.egg-info/dependency_links.txt
telegram_scraper.egg-info/requires.txt
telegram_scraper.egg-info/top_level.txt